qphase_sde/__init__.py
qphase_sde/engine.py
qphase_sde/model.py
qphase_sde/result.py
qphase_sde/state.py
qphase_sde/analyser/__init__.py
qphase_sde/analyser/base.py
qphase_sde/analyser/psd.py
qphase_sde/integrator/__init__.py
qphase_sde/integrator/base.py
qphase_sde/integrator/euler_maruyama.py
qphase_sde/integrator/milstein.py
qphase_sde/integrator/srk.py
qphase_sde-1.0.0.dist-info/licenses/LICENSE
qphase_sde-1.0.0.dist-info/METADATA
qphase_sde-1.0.0.dist-info/WHEEL
qphase_sde-1.0.0.dist-info/entry_points.txt
qphase_sde-1.0.0.dist-info/top_level.txt
qphase_sde-1.0.0.dist-info/RECORD
