Metadata-Version: 2.4
Name: qphase-sde
Version: 1.0.0
Summary: Physics engine for QPhase: Stochastic Differential Equations in Phase Space
Author-email: Yu Xue-Hao <yuxuehao23@mails.ucas.ac.cn>
License: MIT License
Project-URL: Homepage, https://github.com/PolarisMegrez/qphase
Project-URL: Repository, https://github.com/PolarisMegrez/qphase
Project-URL: Issues, https://github.com/PolarisMegrez/qphase/issues
Keywords: quantum optics,SDE,simulation,stochastic,phase-space
Classifier: Programming Language :: Python :: 3
Classifier: Programming Language :: Python :: 3.10
Classifier: Programming Language :: Python :: 3.11
Classifier: Programming Language :: Python :: 3.12
Classifier: License :: OSI Approved :: MIT License
Classifier: Operating System :: OS Independent
Classifier: Intended Audience :: Science/Research
Classifier: Topic :: Scientific/Engineering :: Physics
Classifier: Topic :: Software Development :: Libraries
Requires-Python: >=3.10
License-File: LICENSE
Requires-Dist: numpy>=1.23
Requires-Dist: qphase>=1.0.0
Provides-Extra: accel
Requires-Dist: numba>=0.57; extra == "accel"
Provides-Extra: config
Requires-Dist: pydantic>=2.4; extra == "config"
Dynamic: license-file
